<?xml version="1.0" encoding="UTF-8"?>
<objects serializationModel="Studio.02.02.00">
	<object class="AudioFile" id="{44daf6e0-18e8-4571-bffd-a1d2e8a5b8ba}">
		<property name="assetPath">
			<value>amb_desert_animals_eagle_01.wav</value>
		</property>
		<property name="frequencyInKHz">
			<value>44.0999985</value>
		</property>
		<property name="channelCount">
			<value>2</value>
		</property>
		<property name="length">
			<value>0.53859410430839005</value>
		</property>
		<relationship name="masterAssetFolder">
			<destination>{3de38e6f-da69-451e-89a5-84bff040cc47}</destination>
		</relationship>
	</object>
</objects>
